odoo/addons/converter/README.rst
odoo/addons/converter/__init__.py
odoo/addons/converter/__manifest__.py
odoo/addons/converter/_context.py
odoo/addons/converter/base.py
odoo/addons/converter/biome.json
odoo/addons/converter/exception.py
odoo/addons/converter/field.py
odoo/addons/converter/image.py
odoo/addons/converter/keyfield.py
odoo/addons/converter/list.py
odoo/addons/converter/mail_template.py
odoo/addons/converter/model.py
odoo/addons/converter/py.typed
odoo/addons/converter/qr_code.py
odoo/addons/converter/relation.py
odoo/addons/converter/switch.py
odoo/addons/converter/validate.py
odoo/addons/converter/xref.py
odoo/addons/converter/.badges/code_style-biome-60a5fa.svg
odoo/addons/converter/.badges/code_style-ruff.svg
odoo/addons/converter/.badges/coverage.svg
odoo/addons/converter/.badges/licence-AGPL--3-blue.svg
odoo/addons/converter/.badges/maturity.svg
odoo/addons/converter/.badges/pylint.svg
odoo/addons/converter/i18n/fr.po
odoo/addons/converter/models/__init__.py
odoo/addons/converter/models/ir_model_data.py
odoo/addons/converter/tests/__init__.py
odoo/addons/converter/tests/_common.py
odoo/addons/converter/tests/test_base.py
odoo/addons/converter/tests/test_context.py
odoo/addons/converter/tests/test_converters.py
odoo/addons/converter/tests/test_field.py
odoo/addons/converter/tests/test_ir_model.py
odoo/addons/converter/tests/test_keyfield.py
odoo/addons/converter/tests/test_mail_template.py
odoo/addons/converter/tests/test_model.py
odoo/addons/converter/tests/test_qr_code.py
odoo/addons/converter/tests/test_relation.py
odoo/addons/converter/tests/test_switch.py
odoo/addons/converter/tests/test_validate.py
odoo/addons/converter/tests/schemas/__init__.py
odoo/addons/converter/tests/schemas/product.schema.json
odoo/addons/converter/tests/schemas_dir/product.schema.json
odoo_addon_converter-19.0.1.0.0.dist-info/METADATA
odoo_addon_converter-19.0.1.0.0.dist-info/WHEEL
odoo_addon_converter-19.0.1.0.0.dist-info/licenses/LICENSE
odoo_addon_converter-19.0.1.0.0.dist-info/RECORD
